{
    "Logitech Dual Action":{
      "map":{
      	"13":"RT",
      	"11":"RB",
      	"12":"LT",
      	"10":"LB",
      	"23":"dpad_C",
      	"14":"back",
      	"15":"start",
      	"16":"jsb_L",
      	"17":"jsb_R",
      	"9":"col_U",
      	"6":"col_L",
      	"8":"col_R",
      	"7":"col_D",
      	"19":"js_L_X",
      	"20":"js_L_Y",
      	"21":"js_R_X",
      	"22":"js_R_Y"
      	},
      "range":{
      	"13":"1",
      	"11":"1",
      	"12":"1",
      	"10":"1",
      	"23":"1",
      	"14":"1",
      	"15":"1",
      	"16":"1",
      	"17":"1",
      	"9":"1",
      	"6":"1",
      	"8":"1",
      	"7":"1",
      	"19":"255",
      	"20":"255",
      	"21":"255",
      	"22":"255"
      	}
    }
}
